white_api/__init__.py
white_api/core.py
white_api-1.0.3.dist-info/LICENSE
white_api-1.0.3.dist-info/METADATA
white_api-1.0.3.dist-info/WHEEL
white_api-1.0.3.dist-info/top_level.txt
white_api-1.0.3.dist-info/RECORD
