Metadata-Version: 2.1
Name: white_api
Version: 1.0.3
Summary: Python client for White API (api.wscode.ru)
Author: devinpython
Author-email: krostv321@gmail.com
Keywords: api,white,gifts,stickers,nft,marketplace
Requires-Python: >=3.7
License-File: LICENSE
Requires-Dist: requests>=2.25.0
